k7eela/__init__.py
k7eela/main.py
k7eela-0.1.3.dist-info/METADATA
k7eela-0.1.3.dist-info/WHEEL
k7eela-0.1.3.dist-info/entry_points.txt
k7eela-0.1.3.dist-info/top_level.txt
k7eela-0.1.3.dist-info/RECORD
